[
	{
		"id": 1,
		"start": 123.502,
		"end": 133.502,
		"text": "♪♪～"
	},
	{
		"id": 2,
		"start": 169.03258600000004,
		"end": 173.03658600000006,
		"text": "＜ワンピースを狙う<br />全ての海賊たちが目指す→"
	},
	{
		"id": 3,
		"start": 173.03658600000006,
		"end": 178.03658600000006,
		"text": "グランドライン後半の海<br />人呼んで　新世界＞"
	},
	{
		"id": 4,
		"start": 180.043586,
		"end": 183.04658600000005,
		"text": "＜しかし<br />かつて　その海を制したのは→"
	},
	{
		"id": 5,
		"start": 183.04658600000005,
		"end": 188.05158600000004,
		"text": "海賊王　ゴールド・ロジャー<br />ただ　一人＞"
	},
	{
		"id": 6,
		"start": 188.05158600000004,
		"end": 195.05858600000005,
		"text": "＜新世界は　幾多の海賊たちの<br />夢と野望を阻んできた＞"
	},
	{
		"id": 7,
		"start": 195.05858600000005,
		"end": 199.062586,
		"text": "＜その海に今　ゴムゴムの実を食べゴム人間となった少年→"
	},
	{
		"id": 8,
		"start": 199.062586,
		"end": 203.06658600000003,
		"text": "モンキー・Ｄ・ルフィと<br />その仲間たちが挑む！＞"
	},
	{
		"id": 9,
		"start": 203.06658600000003,
		"end": 207.06658600000003,
		"text": "（ルフィ）海賊王に　俺は　なる！"
	},
	{
		"id": 10,
		"start": 210.07358600000003,
		"end": 214.07758600000005,
		"text": "＜新世界を支配する四皇の一角を<br />崩すため→"
	},
	{
		"id": 11,
		"start": 214.07758600000005,
		"end": 217.08058600000004,
		"text": "トラファルガー・ローと<br />海賊同盟を組んだ　ルフィたちは→"
	},
	{
		"id": 12,
		"start": 217.08058600000004,
		"end": 219.08258600000005,
		"text": "ドレスローザに乗り込むも→"
	},
	{
		"id": 13,
		"start": 219.08258600000005,
		"end": 223.086586,
		"text": "現国王　ドフラミンゴの<br />計略によって→"
	},
	{
		"id": 14,
		"start": 223.086586,
		"end": 225.08858600000002,
		"text": "島ごと閉じ込められてしまう＞"
	},
	{
		"id": 15,
		"start": 225.08858600000002,
		"end": 228.02558600000003,
		"text": "＜さらに　ルフィたち１２名に<br />懸賞金が懸けられ→"
	},
	{
		"id": 16,
		"start": 228.02558600000003,
		"end": 231.02858600000002,
		"text": "全国民から追われる身に＞"
	},
	{
		"id": 17,
		"start": 231.02858600000002,
		"end": 235.03258600000004,
		"text": "＜一味が　ドンキホーテファミリーと<br />激しい戦いを繰り広げる中→"
	},
	{
		"id": 18,
		"start": 235.03258600000004,
		"end": 240.03758600000003,
		"text": "ルフィとローは　王宮で<br />ついに　ドフラミンゴと激突した＞"
	},
	{
		"id": 19,
		"start": 240.03758600000003,
		"end": 243.04058600000002,
		"text": "タコスタンプ！"
	},
	{
		"id": 20,
		"start": 243.04058600000002,
		"end": 247.04458600000004,
		"text": "うおおー！！"
	},
	{
		"id": 21,
		"start": 247.04458600000004,
		"end": 250.04758600000002,
		"text": "＜この戦いに秘めた　ローの思い＞"
	},
	{
		"id": 22,
		"start": 250.04758600000002,
		"end": 254.04758600000002,
		"text": "（ロー）そして　今があるのは<br />コラさんのおかげ！"
	},
	{
		"id": 23,
		"start": 256.05358599999977,
		"end": 258.0555859999997,
		"text": "感謝しているよ。"
	},
	{
		"id": 24,
		"start": 258.0555859999997,
		"end": 261.05858599999976,
		"text": "この力で　お前らを討ち取れる！"
	},
	{
		"id": 25,
		"start": 261.05858599999976,
		"end": 268.0655859999998,
		"text": "＜ローと　ドフラミンゴ<br />物語は　１６年前に　さかのぼる＞"
	},
	{
		"id": 26,
		"start": 268.0655859999998,
		"end": 270.0675859999998,
		"text": "＜余命わずかだった　ローは→"
	},
	{
		"id": 27,
		"start": 270.0675859999998,
		"end": 273.0705859999998,
		"text": "ドンキホーテファミリーに<br />飛び込んだ＞"
	},
	{
		"id": 28,
		"start": 273.0705859999998,
		"end": 278.0755859999998,
		"text": "＜そこで　子供嫌いの物言わぬ男<br />コラソンと出会う＞"
	},
	{
		"id": 29,
		"start": 278.0755859999998,
		"end": 280.07758599999977,
		"text": "（ロー）《いた　コラソン！》→"
	},
	{
		"id": 30,
		"start": 280.07758599999977,
		"end": 284.0815859999998,
		"text": "《俺の親も　妹も<br />教会のみんなも死んだのに→"
	},
	{
		"id": 31,
		"start": 284.0815859999998,
		"end": 288.0185859999998,
		"text": "あんなバカが生きてて<br />いいわけがねえ！》→"
	},
	{
		"id": 32,
		"start": 288.0185859999998,
		"end": 293.0235859999998,
		"text": "《黙ってりゃいい…<br />誰も気にしねえ！》→"
	},
	{
		"id": 33,
		"start": 293.0235859999998,
		"end": 296.0235859999998,
		"text": "《くず一人<br />行方不明になっても！》"
	},
	{
		"id": 34,
		"start": 341.0715859999998,
		"end": 344.0715859999998,
		"text": "（村人）《天竜人の一家だ！》"
	},
	{
		"id": 35,
		"start": 346.09358599999973,
		"end": 349.09358599999973,
		"text": "（村人）《殺してしまえ！》"
	},
	{
		"id": 36,
		"start": 351.0145859999998,
		"end": 355.0185859999998,
		"text": "（村人）《元　天竜人だ。<br />殺しても　海軍は動かねえ》→"
	},
	{
		"id": 37,
		"start": 355.0185859999998,
		"end": 357.02058599999975,
		"text": "《大将も来ねえ！》"
	},
	{
		"id": 38,
		"start": 357.02058599999975,
		"end": 361.0245859999998,
		"text": "（村人）《ありがてえ。<br />報復の機会を与えられた》→"
	},
	{
		"id": 39,
		"start": 361.0245859999998,
		"end": 363.0265859999997,
		"text": "《一生　泣き寝入りと<br />諦めてた！》"
	},
	{
		"id": 40,
		"start": 363.0265859999997,
		"end": 366.02958599999977,
		"text": "（村人）《ハンマーで<br />全身の骨を折ろう》"
	},
	{
		"id": 41,
		"start": 366.02958599999977,
		"end": 368.0315859999997,
		"text": "（村人）《１，０００本の矢を刺そう》"
	},
	{
		"id": 42,
		"start": 368.0315859999997,
		"end": 371.03458599999976,
		"text": "（村人）《駄目だ。簡単に殺すな》→"
	},
	{
		"id": 43,
		"start": 371.03458599999976,
		"end": 374.0375859999997,
		"text": "《ずっと　ずっと　生かして<br />もっと苦しめろ！》"
	},
	{
		"id": 44,
		"start": 374.0375859999997,
		"end": 377.04058599999973,
		"text": "（ドフラミンゴ）《ぐっ…》<br />（村人）《そうだ　生ぬるい！》"
	},
	{
		"id": 45,
		"start": 377.04058599999973,
		"end": 381.04458599999975,
		"text": "（村人）《嫌よ。<br />今すぐ　復讐してやるわ》"
	},
	{
		"id": 46,
		"start": 381.04458599999975,
		"end": 383.0465859999997,
		"text": "《聞け！　お前ら》"
	},
	{
		"id": 47,
		"start": 383.0465859999997,
		"end": 387.0505859999997,
		"text": "《まだ　５歳と２歳だった<br />俺の息子たちが→"
	},
	{
		"id": 48,
		"start": 387.0505859999997,
		"end": 391.05458599999974,
		"text": "天竜人の前を<br />横切ったって理由…》"
	},
	{
		"id": 49,
		"start": 391.05458599999974,
		"end": 395.05858599999976,
		"text": "《たった　それだけの理由で<br />殺されたんだ！》"
	},
	{
		"id": 50,
		"start": 395.05858599999976,
		"end": 399.0625859999998,
		"text": "《奴隷にされた娘が<br />哀れな姿で帰ってきて→"
	},
	{
		"id": 51,
		"start": 399.0625859999998,
		"end": 405.06858599999975,
		"text": "一言も　しゃべらずに<br />３日後に自害したわ！》"
	},
	{
		"id": 52,
		"start": 405.06858599999975,
		"end": 408.0045859999998,
		"text": "《俺は　昔　奴隷だった》"
	},
	{
		"id": 53,
		"start": 408.0045859999998,
		"end": 413.0095859999998,
		"text": "《この両目　お前らが…<br />お前らが！》"
	},
	{
		"id": 54,
		"start": 413.0095859999998,
		"end": 415.01158599999974,
		"text": "《俺の女房を返せ！》"
	},
	{
		"id": 55,
		"start": 415.01158599999974,
		"end": 419.01558599999976,
		"text": "《どうでもいいんだろ　お前らにゃ俺たちの命なんて！》"
	},
	{
		"id": 56,
		"start": 419.01558599999976,
		"end": 423.0195859999998,
		"text": "（村人）《お前らに納める<br />天上金のせいで→"
	},
	{
		"id": 57,
		"start": 423.0195859999998,
		"end": 425.02158599999973,
		"text": "国が　飢餓で滅んだんだ！》→"
	},
	{
		"id": 58,
		"start": 425.02158599999973,
		"end": 428.0245859999998,
		"text": "《お前ら<br />腹　減ったことあるか？》→"
	},
	{
		"id": 59,
		"start": 428.0245859999998,
		"end": 431.0275859999997,
		"text": "《みんな　骨と皮になって<br />死んだんだよ！》"
	},
	{
		"id": 60,
		"start": 431.0275859999997,
		"end": 436.0325859999997,
		"text": "《神も同然なんだろ？<br />人間とは違うんだろ？》→"
	},
	{
		"id": 61,
		"start": 436.0325859999997,
		"end": 440.0365859999997,
		"text": "《これくらいじゃ<br />死なねえよな！？》"
	},
	{
		"id": 62,
		"start": 440.0365859999997,
		"end": 442.0385859999998,
		"text": "（ドフラミンゴ）《ギャー！》<br />（ホーミング）《ドフィ！》"
	},
	{
		"id": 63,
		"start": 442.0385859999998,
		"end": 444.04058599999973,
		"text": "（ロシナンテ）《兄上！》"
	},
	{
		"id": 64,
		"start": 444.04058599999973,
		"end": 446.0425859999998,
		"text": "《チクショー》→"
	},
	{
		"id": 65,
		"start": 446.0425859999998,
		"end": 451.0475859999998,
		"text": "《人間を<br />虫けら以下に扱いやがって…》→"
	},
	{
		"id": 66,
		"start": 451.0475859999998,
		"end": 456.0525859999998,
		"text": "《苦しいって　悲しいって<br />つらいって　何だか知ってるか？》→"
	},
	{
		"id": 67,
		"start": 456.0525859999998,
		"end": 460.0565859999997,
		"text": "《おい！　天竜人！！》"
	},
	{
		"id": 68,
		"start": 460.0565859999997,
		"end": 474.0045859999998,
		"text": "♪♪～"
	},
	{
		"id": 69,
		"start": 474.0045859999998,
		"end": 476.00658599999974,
		"text": "（ドフラミンゴ）《ギャー！》"
	},
	{
		"id": 70,
		"start": 476.00658599999974,
		"end": 487.0175859999997,
		"text": "[TEL]"
	},
	{
		"id": 71,
		"start": 487.0175859999997,
		"end": 491.02158599999973,
		"text": "（ドフラミンゴ）ハァ　ハァ　ハァ…。"
	},
	{
		"id": 72,
		"start": 491.02158599999973,
		"end": 509.02158599999973,
		"text": "[TEL]"
	},
	{
		"id": 73,
		"start": 512.0425859999998,
		"end": 517.0475859999998,
		"text": "[TEL]"
	},
	{
		"id": 74,
		"start": 517.0475859999998,
		"end": 520.0505859999997,
		"text": "（ドフラミンゴ）どうした？→"
	},
	{
		"id": 75,
		"start": 520.0505859999997,
		"end": 523.0535859999998,
		"text": "ローが？→"
	},
	{
		"id": 76,
		"start": 523.0535859999998,
		"end": 526.0725859999998,
		"text": "そうか。<br />[TEL]（通話を切る音）"
	},
	{
		"id": 77,
		"start": 526.0725859999998,
		"end": 528.0725859999998,
		"text": "（ドフラミンゴ）フゥ…。"
	},
	{
		"id": 78,
		"start": 539.0025859999997,
		"end": 541.0045859999998,
		"text": "（天竜人たち）あっ…。"
	},
	{
		"id": 79,
		"start": 541.0045859999998,
		"end": 545.0085859999997,
		"text": "（天竜人）正気か　ホーミング聖！<br />あなたともあろう者が。"
	},
	{
		"id": 80,
		"start": 545.0085859999997,
		"end": 549.0125859999997,
		"text": "（天竜人）神の地位を捨て<br />人間に成り下がろうというのか！"
	},
	{
		"id": 81,
		"start": 549.0125859999997,
		"end": 552.0155859999998,
		"text": "（ホーミング）人間ですよ　昔から。"
	},
	{
		"id": 82,
		"start": 552.0155859999998,
		"end": 555.0185859999998,
		"text": "われわれも　そうだと<br />言いたいのかえ？"
	},
	{
		"id": 83,
		"start": 555.0185859999998,
		"end": 558.0215859999997,
		"text": "冒涜だ！　天竜人を　何と心得る！"
	},
	{
		"id": 84,
		"start": 558.0215859999997,
		"end": 562.0255859999997,
		"text": "裏切り者め！<br />お前は昔から　異端だった。"
	},
	{
		"id": 85,
		"start": 562.0255859999997,
		"end": 565.0285859999998,
		"text": "（天竜人）そうだ　裏切り者！"
	},
	{
		"id": 86,
		"start": 565.0285859999998,
		"end": 570.0335859999998,
		"text": "どう思われようと構いませんよ。<br />人間は素晴らしい。"
	},
	{
		"id": 87,
		"start": 570.0335859999998,
		"end": 576.0395859999998,
		"text": "人間として生きる方が<br />はるかに　命の充実を感じられる。"
	},
	{
		"id": 88,
		"start": 576.0395859999998,
		"end": 580.0435859999998,
		"text": "（ホーミング）私は　そう思うのです。"
	},
	{
		"id": 89,
		"start": 580.0435859999998,
		"end": 583.0465859999997,
		"text": "（天竜人）く～　何だと！？<br />（天竜人）生意気だえ。"
	},
	{
		"id": 90,
		"start": 583.0465859999997,
		"end": 587.9845859999997,
		"text": "（天竜人）マリージョアから<br />早く出ていけ！"
	},
	{
		"id": 91,
		"start": 587.9845859999997,
		"end": 591.9885859999997,
		"text": "（役人）われわれが<br />お送りできるのは　ここまでです。"
	},
	{
		"id": 92,
		"start": 591.9885859999997,
		"end": 596.9935859999997,
		"text": "（役人）ここは　北の果て<br />世界政府　非加盟国。→"
	},
	{
		"id": 93,
		"start": 596.9935859999997,
		"end": 599.9965859999998,
		"text": "不自由のない住まいと財産は<br />あちらに。"
	},
	{
		"id": 94,
		"start": 599.9965859999998,
		"end": 601.9985859999997,
		"text": "（ホーミング）ありがとう。　十分だ。"
	},
	{
		"id": 95,
		"start": 601.9985859999997,
		"end": 605.9985859999997,
		"text": "（役人）では　天竜人の証明チップを回収します。"
	},
	{
		"id": 96,
		"start": 615.0115859999997,
		"end": 619.0155859999998,
		"text": "さあ　ここで　一家４人<br />つつましく　暮らそう。"
	},
	{
		"id": 97,
		"start": 619.0155859999998,
		"end": 623.0195859999998,
		"text": "（ドフラミンゴの母）まずは<br />荷ほどきを始めましょう。"
	},
	{
		"id": 98,
		"start": 623.0195859999998,
		"end": 626.0225859999997,
		"text": "（ドフラミンゴ）父上<br />奴隷は　どこだえ？→"
	},
	{
		"id": 99,
		"start": 626.0225859999997,
		"end": 629.0255859999997,
		"text": "片付けなんか<br />奴隷にやらせればいいんだえ。"
	},
	{
		"id": 100,
		"start": 629.0255859999997,
		"end": 631.0275859999997,
		"text": "（ロシナンテ）うわっ。<br />（ドフラミンゴ）いないんなら→"
	},
	{
		"id": 101,
		"start": 631.0275859999997,
		"end": 634.0305859999997,
		"text": "買いに行こうえ。<br />（ホーミング）ハァ…。"
	},
	{
		"id": 102,
		"start": 634.0305859999997,
		"end": 640.0365859999997,
		"text": "ドフィ　ロシナンテ<br />お前たちには　一から教えねばな。"
	},
	{
		"id": 103,
		"start": 640.0365859999997,
		"end": 642.0365859999997,
		"text": "（ロシナンテ）うわ…。"
	},
	{
		"id": 104,
		"start": 644.0405859999997,
		"end": 646.0595859999997,
		"text": "（ドフラミンゴの母）よく似合うわよ<br />ドフィ。"
	},
	{
		"id": 105,
		"start": 646.0595859999997,
		"end": 650.9815859999998,
		"text": "（ドフラミンゴ）嫌だ！　こんなの嫌だ。<br />奴隷みたいだえ。"
	},
	{
		"id": 106,
		"start": 650.9815859999998,
		"end": 653.9845859999997,
		"text": "よさないか。<br />（ドフラミンゴ）やだよ　父上　嫌だえ。"
	},
	{
		"id": 107,
		"start": 653.9845859999997,
		"end": 655.9865859999998,
		"text": "こんなの着たら　においが　つくえ。"
	},
	{
		"id": 108,
		"start": 655.9865859999998,
		"end": 660.9915859999998,
		"text": "（ホーミング）ドフィ。　私たちは<br />人間として暮らしていくんだ。"
	},
	{
		"id": 109,
		"start": 660.9915859999998,
		"end": 663.9945859999998,
		"text": "（ドフラミンゴ）人間？<br />（ホーミング）マリージョアよりも→"
	},
	{
		"id": 110,
		"start": 663.9945859999998,
		"end": 666.9975859999997,
		"text": "はるかに豊かな生活を送るんだよ。"
	},
	{
		"id": 111,
		"start": 666.9975859999997,
		"end": 670.0005859999998,
		"text": "豊かっていうのは<br />物があるってことじゃない。"
	},
	{
		"id": 112,
		"start": 670.0005859999998,
		"end": 675.0005859999998,
		"text": "心のことなんだ。<br />（ドフラミンゴ）うっ…。"
	},
	{
		"id": 113,
		"start": 677.0075859999997,
		"end": 679.0095859999998,
		"text": "（店主）はい　リンゴ　２つね。"
	},
	{
		"id": 114,
		"start": 679.0095859999998,
		"end": 682.0125859999997,
		"text": "失礼。　食材を買い求めたい。"
	},
	{
		"id": 115,
		"start": 682.0125859999997,
		"end": 684.0145859999998,
		"text": "おや　見ない顔だね。"
	},
	{
		"id": 116,
		"start": 684.0145859999998,
		"end": 688.0185859999998,
		"text": "はい。　このたび　マリージョアより<br />引っ越してまいりました→"
	},
	{
		"id": 117,
		"start": 688.0185859999998,
		"end": 691.0215859999997,
		"text": "ドンキホーテ・ホーミングと<br />申します。"
	},
	{
		"id": 118,
		"start": 691.0215859999997,
		"end": 693.0235859999998,
		"text": "（市民・店主）えっ…。<br />（市民たち）あっ…。"
	},
	{
		"id": 119,
		"start": 693.0235859999998,
		"end": 697.0275859999997,
		"text": "マ…　マリージョアって。<br />（ドフラミンゴ）んっ？"
	},
	{
		"id": 120,
		"start": 697.0275859999997,
		"end": 699.0295859999998,
		"text": "あっ　あんた　天竜人かい？"
	},
	{
		"id": 121,
		"start": 699.0295859999998,
		"end": 705.0355859999997,
		"text": "その肩書は　もう捨てました。<br />これからは人間です。→"
	},
	{
		"id": 122,
		"start": 705.0355859999997,
		"end": 709.9735859999997,
		"text": "私たちは　皆さんと<br />仲良くしたいのです。"
	},
	{
		"id": 123,
		"start": 709.9735859999997,
		"end": 711.9735859999997,
		"text": "うっ…。"
	},
	{
		"id": 124,
		"start": 713.9775859999997,
		"end": 716.9805859999998,
		"text": "おい！　なぜ　ひれ伏さねえ！"
	},
	{
		"id": 125,
		"start": 716.9805859999998,
		"end": 720.9845859999997,
		"text": "貴様ら　無礼だぞ。<br />俺の前を横切ったな。"
	},
	{
		"id": 126,
		"start": 720.9845859999997,
		"end": 725.9895859999997,
		"text": "誰か　ピストルをもて！<br />俺を　誰だと思ってんだ！→"
	},
	{
		"id": 127,
		"start": 725.9895859999997,
		"end": 729.9935859999997,
		"text": "おい　お前ら！"
	},
	{
		"id": 128,
		"start": 729.9935859999997,
		"end": 732.9965859999998,
		"text": "（市民）天竜人は　どこだ！<br />（市民）捜し出せ！"
	},
	{
		"id": 129,
		"start": 732.9965859999998,
		"end": 734.9985859999997,
		"text": "（市民）つるし上げろ！"
	},
	{
		"id": 130,
		"start": 734.9985859999997,
		"end": 739.0025859999997,
		"text": "（ドフラミンゴ）《父上　あいつら<br />何で　ひれ伏さないのかえ》"
	},
	{
		"id": 131,
		"start": 739.0025859999997,
		"end": 741.0025859999997,
		"text": "あっ…。"
	},
	{
		"id": 132,
		"start": 744.0075859999997,
		"end": 746.0095859999998,
		"text": "あっ…。"
	},
	{
		"id": 133,
		"start": 746.0095859999998,
		"end": 749.0125859999997,
		"text": "ぐっ…。"
	},
	{
		"id": 134,
		"start": 749.0125859999997,
		"end": 752.0155859999998,
		"text": "（市民）中には　いない。<br />逃げたぞ。　捜せ！→"
	},
	{
		"id": 135,
		"start": 752.0155859999998,
		"end": 754.0175859999997,
		"text": "まだ　近くに　いるはずだ！"
	},
	{
		"id": 136,
		"start": 754.0175859999997,
		"end": 756.0195859999998,
		"text": "殺すなよ。　生かして苦しめろ！"
	},
	{
		"id": 137,
		"start": 756.0195859999998,
		"end": 758.0215859999997,
		"text": "（一同）お～！"
	},
	{
		"id": 138,
		"start": 758.0215859999997,
		"end": 762.0255859999997,
		"text": "（市民）数百年分の世界の恨みを<br />あの一家に刻み込め！"
	},
	{
		"id": 139,
		"start": 762.0255859999997,
		"end": 765.0255859999997,
		"text": "（一同）お～！<br />（ホーミング）あっ…。"
	},
	{
		"id": 140,
		"start": 769.0325859999997,
		"end": 773.0325859999997,
		"text": "（市民）待て！　逃がすな！"
	},
	{
		"id": 141,
		"start": 779.0425859999998,
		"end": 781.0445859999998,
		"text": "あっ！"
	},
	{
		"id": 142,
		"start": 781.0445859999998,
		"end": 783.0445859999998,
		"text": "（ホーミング・ドフラミンゴの母）ドフィ！"
	},
	{
		"id": 143,
		"start": 785.0485859999998,
		"end": 791.0485859999998,
		"text": "（ドフラミンゴ）《父上<br />なぜ　追われるのかえ》"
	},
	{
		"id": 144,
		"start": 795.0585859999998,
		"end": 798.0615859999997,
		"text": "（ホーミング）雨露を　しのげるだけで<br />ありがたい。→"
	},
	{
		"id": 145,
		"start": 798.0615859999997,
		"end": 803.0665859999998,
		"text": "ここらの地域には　われわれの噂はまだ届いていない。→"
	},
	{
		"id": 146,
		"start": 803.0665859999998,
		"end": 805.0685859999998,
		"text": "しばらく　ここで…。<br />（ドフラミンゴ）嫌だ！→"
	},
	{
		"id": 147,
		"start": 805.0685859999998,
		"end": 808.0715859999998,
		"text": "こんな汚い所で<br />生きていけるわけないえ！→"
	},
	{
		"id": 148,
		"start": 808.0715859999998,
		"end": 813.0715859999998,
		"text": "家の中にも虫が。<br />家の　においも　吐き気がするえ！"
	},
	{
		"id": 149,
		"start": 823.0865859999998,
		"end": 826.0865859999998,
		"text": "（寝息）"
	},
	{
		"id": 150,
		"start": 829.0255859999997,
		"end": 831.0275859999997,
		"text": "（市民）捜し出せ！　あの一家を。"
	},
	{
		"id": 151,
		"start": 831.0275859999997,
		"end": 833.0295859999998,
		"text": "まだ　その辺に　いるはずだ！"
	},
	{
		"id": 152,
		"start": 833.0295859999998,
		"end": 837.0335859999998,
		"text": "（ホーミング）あっ！<br />（市民）見つけしだい　殺せ！"
	},
	{
		"id": 153,
		"start": 837.0335859999998,
		"end": 841.0335859999998,
		"text": "逃げるんだ　今すぐ！<br />（ドフラミンゴ）あっ…。"
	},
	{
		"id": 154,
		"start": 860.1884399999998,
		"end": 862.1904399999997,
		"text": "（ホーミング）<br />ここまでのことになるとは→"
	},
	{
		"id": 155,
		"start": 862.1904399999997,
		"end": 864.1924399999997,
		"text": "想定できなかった。"
	},
	{
		"id": 156,
		"start": 864.1924399999997,
		"end": 866.1944399999999,
		"text": "私が甘かったんだ。"
	},
	{
		"id": 157,
		"start": 866.1944399999999,
		"end": 871.1994399999998,
		"text": "頼む。　何でもする。<br />妻と子供だけでいい。→"
	},
	{
		"id": 158,
		"start": 871.1994399999998,
		"end": 874.2024399999997,
		"text": "マリージョアへ<br />帰らせてくれないか？→"
	},
	{
		"id": 159,
		"start": 874.2024399999997,
		"end": 878.2064399999998,
		"text": "このままでは<br />一家全員　殺されてしまう。"
	},
	{
		"id": 160,
		"start": 878.2064399999998,
		"end": 882.2104399999997,
		"text": "[TEL]（天竜人）君が選んだ人生だえ。<br />捨てたものは戻らない。→"
	},
	{
		"id": 161,
		"start": 882.2104399999997,
		"end": 886.2144399999999,
		"text": "もう二度と　かけてくるな。<br />人間の分際で！"
	},
	{
		"id": 162,
		"start": 886.2144399999999,
		"end": 890.2144399999999,
		"text": "（ホーミング）まっ　待ってくれ。　頼む！<br />[TEL]（通話の切れる音）"
	},
	{
		"id": 163,
		"start": 894.2224399999997,
		"end": 896.2244399999998,
		"text": "（一同）ハハハ…。"
	},
	{
		"id": 164,
		"start": 896.2244399999998,
		"end": 899.2274399999998,
		"text": "このパン泥棒め。<br />（一同）ハハハ…。"
	},
	{
		"id": 165,
		"start": 899.2274399999998,
		"end": 902.2304399999997,
		"text": "（ドフラミンゴ）うっ…。"
	},
	{
		"id": 166,
		"start": 902.2304399999997,
		"end": 908.2304399999997,
		"text": "（ドフラミンゴ）《父上<br />生まれて初めて　痛いえ》"
	},
	{
		"id": 167,
		"start": 913.1754399999999,
		"end": 920.1754399999999,
		"text": "（ドフラミンゴ）《父上<br />生まれて初めて　腹が減ったえ》"
	},
	{
		"id": 168,
		"start": 924.1864399999998,
		"end": 929.1914399999997,
		"text": "（ドフラミンゴ）早く食え。　ロシー。<br />人が来る。"
	},
	{
		"id": 169,
		"start": 929.1914399999997,
		"end": 931.1934399999997,
		"text": "うっ…。"
	},
	{
		"id": 170,
		"start": 931.1934399999997,
		"end": 933.1954399999998,
		"text": "（ドフラミンゴ）母上　食べ物だえ。"
	},
	{
		"id": 171,
		"start": 933.1954399999998,
		"end": 935.1974399999998,
		"text": "（ドフラミンゴの母）ドフィ　ロシー。"
	},
	{
		"id": 172,
		"start": 935.1974399999998,
		"end": 938.2004399999997,
		"text": "（せき）<br />（ロシナンテ・ドフラミンゴ）母上！"
	},
	{
		"id": 173,
		"start": 938.2004399999997,
		"end": 944.2064399999998,
		"text": "ごめんね　少し　体調が…。<br />（ドフラミンゴの母の　せき）"
	},
	{
		"id": 174,
		"start": 944.2064399999998,
		"end": 953.2154399999998,
		"text": "（ロシナンテの泣き声）"
	},
	{
		"id": 175,
		"start": 953.2154399999998,
		"end": 961.2234399999999,
		"text": "（ドフラミンゴ）《父上<br />母上は…　死んだえ》"
	},
	{
		"id": 176,
		"start": 961.2234399999999,
		"end": 963.2254399999998,
		"text": "（村人）捕まえたぞ！！"
	},
	{
		"id": 177,
		"start": 963.2254399999998,
		"end": 970.1654399999999,
		"text": "子供たちは許してくれ！<br />私だけにしてくれ～！→"
	},
	{
		"id": 178,
		"start": 970.1654399999999,
		"end": 973.1654399999999,
		"text": "うっ…　頼む　頼む！"
	},
	{
		"id": 179,
		"start": 982.1774399999998,
		"end": 984.1774399999998,
		"text": "（ドフラミンゴ）《父上！》"
	},
	{
		"id": 180,
		"start": 986.1814399999997,
		"end": 988.1814399999997,
		"text": "（ドフラミンゴ）《うっ…》"
	},
	{
		"id": 181,
		"start": 990.1854399999999,
		"end": 992.1854399999999,
		"text": "ぐっ…。"
	},
	{
		"id": 182,
		"start": 998.1934399999997,
		"end": 1006.1934399999997,
		"text": "（ドフラミンゴ）《お前！！<br />何てことしてくれたんだえ！！》"
	},
	{
		"id": 183,
		"start": 1009.2044399999999,
		"end": 1013.2084399999998,
		"text": "（ジョーラ）若さま。<br />ローを捕らえてきたざます。→"
	},
	{
		"id": 184,
		"start": 1013.2084399999998,
		"end": 1016.2114399999997,
		"text": "急に　脱走する気に<br />なったようざますね。"
	},
	{
		"id": 185,
		"start": 1016.2114399999997,
		"end": 1018.2134399999997,
		"text": "（ロー）くそ！　放せ～！→"
	},
	{
		"id": 186,
		"start": 1018.2134399999997,
		"end": 1022.2174399999998,
		"text": "うわっ。<br />（マッハバイス）港まで逃げてたイーン。"
	},
	{
		"id": 187,
		"start": 1022.2174399999998,
		"end": 1025.2204400000005,
		"text": "（バッファロー）コラさん刺した件で<br />拷問が始まるだすやん。"
	},
	{
		"id": 188,
		"start": 1025.2204400000005,
		"end": 1028.2234400000007,
		"text": "（ベビー５）ローは<br />かわいそうな子なのに…。"
	},
	{
		"id": 189,
		"start": 1028.2234400000007,
		"end": 1030.1584400000006,
		"text": "（ロー）くっ…。"
	},
	{
		"id": 190,
		"start": 1030.1584400000006,
		"end": 1032.1584400000006,
		"text": "（ロー）あっ！"
	},
	{
		"id": 191,
		"start": 1034.1624400000005,
		"end": 1037.1654400000007,
		"text": "（ロー）《コラソン…》→"
	},
	{
		"id": 192,
		"start": 1037.1654400000007,
		"end": 1040.1684400000008,
		"text": "《くそ！　死ななかったのか》→"
	},
	{
		"id": 193,
		"start": 1040.1684400000008,
		"end": 1043.1714400000005,
		"text": "《これじゃあ<br />俺の死に損じゃねえか》→"
	},
	{
		"id": 194,
		"start": 1043.1714400000005,
		"end": 1046.1744400000007,
		"text": "《バッファローは<br />アイスで買収したのに》→"
	},
	{
		"id": 195,
		"start": 1046.1744400000007,
		"end": 1049.1774400000008,
		"text": "《自分で　チクりやがったな》→"
	},
	{
		"id": 196,
		"start": 1049.1774400000008,
		"end": 1053.1814400000007,
		"text": "《確かに<br />刃は　体を貫いたはず》→"
	},
	{
		"id": 197,
		"start": 1053.1814400000007,
		"end": 1056.1844400000004,
		"text": "《平然としやがって！》"
	},
	{
		"id": 198,
		"start": 1056.1844400000004,
		"end": 1058.1864400000009,
		"text": "（ドフラミンゴ）ロー。<br />（ロー）くっ…。"
	},
	{
		"id": 199,
		"start": 1058.1864400000009,
		"end": 1062.1904400000008,
		"text": "（ドフラミンゴ）お前を<br />ここへ呼んだのは　他でもねえ。→"
	},
	{
		"id": 200,
		"start": 1062.1904400000008,
		"end": 1064.1924400000007,
		"text": "お前を　正式に→"
	},
	{
		"id": 201,
		"start": 1064.1924400000007,
		"end": 1068.1964400000006,
		"text": "ドンキホーテファミリーの一員に<br />迎えることにした。"
	},
	{
		"id": 202,
		"start": 1068.1964400000006,
		"end": 1070.1984400000006,
		"text": "えっ？<br />（ベビー５・バッファロー）えっ！"
	},
	{
		"id": 203,
		"start": 1070.1984400000006,
		"end": 1074.1984400000006,
		"text": "（マッハバイス）ファミリーだイーン。<br />（ジョーラ）アハッ。"
	},
	{
		"id": 204,
		"start": 1076.204440000001,
		"end": 1084.204440000001,
		"text": "（ドフラミンゴ）最悪の体験から生まれる<br />その無類の　くそみてえな目つき。"
	},
	{
		"id": 205,
		"start": 1086.2144400000006,
		"end": 1088.2164400000006,
		"text": "（ドフラミンゴ）お前には　素質がある。"
	},
	{
		"id": 206,
		"start": 1088.2164400000006,
		"end": 1093.1544400000007,
		"text": "（ジョーラ）オッホッホ…。<br />見込まれたわね　あーた。→"
	},
	{
		"id": 207,
		"start": 1093.1544400000007,
		"end": 1096.1574400000009,
		"text": "若さまは　将来を見抜く男よ。"
	},
	{
		"id": 208,
		"start": 1096.1574400000009,
		"end": 1100.1614400000008,
		"text": "（ロー）《コラソンのこと<br />まだ知らねえのか？》→"
	},
	{
		"id": 209,
		"start": 1100.1614400000008,
		"end": 1105.1664400000009,
		"text": "《何で？　あいつ<br />書いて　報告もできるだろ》→"
	},
	{
		"id": 210,
		"start": 1105.1664400000009,
		"end": 1107.1664400000009,
		"text": "《どういうつもりだ？》"
	},
	{
		"id": 211,
		"start": 1109.1704400000008,
		"end": 1115.1764400000006,
		"text": "将来を見込まれても<br />どうせ　３年後に俺は　死ぬ！"
	},
	{
		"id": 212,
		"start": 1115.1764400000006,
		"end": 1119.1804400000005,
		"text": "（ドフラミンゴ）フフフ…。<br />それは　お前の　運しだい。"
	},
	{
		"id": 213,
		"start": 1119.1804400000005,
		"end": 1121.1824400000005,
		"text": "運？"
	},
	{
		"id": 214,
		"start": 1121.1824400000005,
		"end": 1124.1854400000007,
		"text": "（ドフラミンゴ）うちは<br />闇取引が専門でな。→"
	},
	{
		"id": 215,
		"start": 1124.1854400000007,
		"end": 1127.1884400000008,
		"text": "悪魔の実も取り扱ってる。→"
	},
	{
		"id": 216,
		"start": 1127.1884400000008,
		"end": 1131.1924400000007,
		"text": "実の能力ってのは<br />時に　人知を超える。→"
	},
	{
		"id": 217,
		"start": 1131.1924400000007,
		"end": 1135.1964400000006,
		"text": "お前の病気を治せる能力も<br />あるかもしれない。"
	},
	{
		"id": 218,
		"start": 1135.1964400000006,
		"end": 1137.1984400000006,
		"text": "悪魔の実…。"
	},
	{
		"id": 219,
		"start": 1137.1984400000006,
		"end": 1140.2014400000007,
		"text": "お前が　運を持っていれば→"
	},
	{
		"id": 220,
		"start": 1140.2014400000007,
		"end": 1143.204440000001,
		"text": "リミット３年の間に流れてくる<br />悪魔の実に→"
	},
	{
		"id": 221,
		"start": 1143.204440000001,
		"end": 1146.2074400000006,
		"text": "命を救われる可能性はある。"
	},
	{
		"id": 222,
		"start": 1146.2074400000006,
		"end": 1151.146440000001,
		"text": "俺は　お前を<br />１０年後の俺の右腕として→"
	},
	{
		"id": 223,
		"start": 1151.146440000001,
		"end": 1153.1484400000008,
		"text": "鍛え上げてやる。"
	},
	{
		"id": 224,
		"start": 1153.1484400000008,
		"end": 1156.1514400000005,
		"text": "（コラソンのせき）<br />（コラソン）うっ…。"
	},
	{
		"id": 225,
		"start": 1156.1514400000005,
		"end": 1159.1514400000005,
		"text": "（ドフラミンゴ）どうした？<br />（３人）あっ…。"
	},
	{
		"id": 226,
		"start": 1161.1564400000007,
		"end": 1163.1584400000006,
		"text": "（３人）えっ？<br />（ドフラミンゴ）やられたのか？→"
	},
	{
		"id": 227,
		"start": 1163.1584400000006,
		"end": 1166.1584400000006,
		"text": "始末は　つけたんだろうな？"
	},
	{
		"id": 228,
		"start": 1168.1634400000007,
		"end": 1172.1634400000007,
		"text": "ならいいが　手当てしとけよ。"
	},
	{
		"id": 229,
		"start": 1174.1694400000006,
		"end": 1179.1744400000007,
		"text": "（ロー）《あいつ<br />俺を　かばったのか？》→"
	},
	{
		"id": 230,
		"start": 1179.1744400000007,
		"end": 1182.1744400000007,
		"text": "《何　考えてんだ　あいつ》"
	},
	{
		"id": 231,
		"start": 1184.1794400000008,
		"end": 1188.1834400000007,
		"text": "南東　リヴァース　マウンテンへ向け<br />拠点を移しつつ→"
	},
	{
		"id": 232,
		"start": 1188.1834400000007,
		"end": 1191.1864400000009,
		"text": "取引を拡大していく。"
	},
	{
		"id": 233,
		"start": 1191.1864400000009,
		"end": 1211.1394400000008,
		"text": "♪♪～"
	},
	{
		"id": 234,
		"start": 1211.1394400000008,
		"end": 1231.1594400000008,
		"text": "♪♪～"
	},
	{
		"id": 235,
		"start": 1231.1594400000008,
		"end": 1251.1794400000008,
		"text": "♪♪～"
	},
	{
		"id": 236,
		"start": 1251.1794400000008,
		"end": 1266.1794400000008,
		"text": "♪♪～"
	},
	{
		"id": 237,
		"start": 1268.1964400000006,
		"end": 1271.1324400000008,
		"text": "（ベビー５）私たち<br />本名　教えたじゃない。"
	},
	{
		"id": 238,
		"start": 1271.1324400000008,
		"end": 1273.1344400000007,
		"text": "（ロー）別に　興味ねえよ。"
	},
	{
		"id": 239,
		"start": 1273.1344400000007,
		"end": 1276.1374400000009,
		"text": "ノリ悪～い。　楽しくない。"
	},
	{
		"id": 240,
		"start": 1276.1374400000009,
		"end": 1280.1414400000008,
		"text": "楽しんだって<br />どうせ　俺は死ぬんだ。"
	},
	{
		"id": 241,
		"start": 1280.1414400000008,
		"end": 1282.1434400000007,
		"text": "だいぶ　白いとこ増えてきたね。"
	},
	{
		"id": 242,
		"start": 1282.1434400000007,
		"end": 1286.1474400000006,
		"text": "あと１年　持つかな…。"
	},
	{
		"id": 243,
		"start": 1286.1474400000006,
		"end": 1291.1524400000008,
		"text": "俺の計算より　死期　早えかも。"
	},
	{
		"id": 244,
		"start": 1291.1524400000008,
		"end": 1295.1564400000007,
		"text": "それより　本名あるなら<br />教えろだすやん。"
	},
	{
		"id": 245,
		"start": 1295.1564400000007,
		"end": 1298.1594400000008,
		"text": "２年前　コラさん刺したの<br />若にチクるぞ。"
	},
	{
		"id": 246,
		"start": 1298.1594400000008,
		"end": 1300.1594400000008,
		"text": "チクるぞ。"
	},
	{
		"id": 247,
		"start": 1303.1644400000005,
		"end": 1306.1674400000006,
		"text": "（ロー）フゥ…。"
	},
	{
		"id": 248,
		"start": 1306.1674400000006,
		"end": 1312.1734400000005,
		"text": "トラファルガー・Ｄ・ワーテル・ロー。（ベビー５・バッファロー）えっ…。"
	},
	{
		"id": 249,
		"start": 1312.1734400000005,
		"end": 1317.1784400000006,
		"text": "本当は<br />人に教えちゃいけねえ名前なんだ。"
	},
	{
		"id": 250,
		"start": 1317.1784400000006,
		"end": 1320.1814400000007,
		"text": "お前らみたいに<br />コードネームじゃねえから→"
	},
	{
		"id": 251,
		"start": 1320.1814400000007,
		"end": 1322.1834400000007,
		"text": "別に変わらねえよ。"
	},
	{
		"id": 252,
		"start": 1322.1834400000007,
		"end": 1325.1864400000009,
		"text": "「Ｄ」は　隠し名<br />「ワーテル」は　忌み名で→"
	},
	{
		"id": 253,
		"start": 1325.1864400000009,
		"end": 1327.1884400000008,
		"text": "うちの家族は代々…。"
	},
	{
		"id": 254,
		"start": 1327.1884400000008,
		"end": 1331.1254400000007,
		"text": "何だ　あんまし面白くない。<br />（バッファロー）ホントだすやん。"
	},
	{
		"id": 255,
		"start": 1331.1254400000007,
		"end": 1333.1274400000007,
		"text": "（ロー）お前らが<br />しつこく聞いたよな！"
	},
	{
		"id": 256,
		"start": 1333.1274400000007,
		"end": 1336.1304400000008,
		"text": "（泣き声）"
	},
	{
		"id": 257,
		"start": 1336.1304400000008,
		"end": 1338.1324400000008,
		"text": "うわ！　おい　放せ！→"
	},
	{
		"id": 258,
		"start": 1338.1324400000008,
		"end": 1342.1364400000007,
		"text": "何だ…　コラソン　何の用だ！<br />おい！"
	},
	{
		"id": 259,
		"start": 1342.1364400000007,
		"end": 1344.1384400000006,
		"text": "あ～　また　いじめられる。"
	},
	{
		"id": 260,
		"start": 1344.1384400000006,
		"end": 1348.1384400000006,
		"text": "いつもより　怖え顔してたぞ<br />コラさん。"
	},
	{
		"id": 261,
		"start": 1351.1454400000007,
		"end": 1353.1454400000007,
		"text": "（ロー）うっ…。"
	},
	{
		"id": 262,
		"start": 1357.1514400000005,
		"end": 1361.1514400000005,
		"text": "（ロー）何だよ　コラソン！<br />やんのか！？"
	},
	{
		"id": 263,
		"start": 1363.1574400000009,
		"end": 1366.1574400000009,
		"text": "どうした？　かかってこい！"
	},
	{
		"id": 264,
		"start": 1372.1664400000009,
		"end": 1376.1704400000008,
		"text": "（コラソン）さっきの話は　本当か？<br />（ロー）えっ？→"
	},
	{
		"id": 265,
		"start": 1376.1704400000008,
		"end": 1379.1734400000005,
		"text": "えっ…　誰だ！"
	},
	{
		"id": 266,
		"start": 1379.1734400000005,
		"end": 1385.1794400000008,
		"text": "（コラソン）隠し名　「Ｄ」<br />それが本当なら　出ていけ！→"
	},
	{
		"id": 267,
		"start": 1385.1794400000008,
		"end": 1388.1824400000005,
		"text": "ドフィから離れろ！<br />（ロー）あっ…。"
	},
	{
		"id": 268,
		"start": 1388.1824400000005,
		"end": 1392.1204400000006,
		"text": "ロー！　お前は<br />あいつと一緒にいちゃ→"
	},
	{
		"id": 269,
		"start": 1392.1204400000006,
		"end": 1394.1224400000006,
		"text": "いけねえ人間だ！"
	},
	{
		"id": 270,
		"start": 1394.1224400000006,
		"end": 1396.1224400000006,
		"text": "あっ…。"
	},
	{
		"id": 271,
		"start": 1401.1294400000006,
		"end": 1405.1334400000005,
		"text": "＜病気を治す　すべを　求めて<br />旅立った　ローと　コラソンの前に→"
	},
	{
		"id": 272,
		"start": 1405.1334400000005,
		"end": 1408.1364400000007,
		"text": "想像を絶する困難が待ち受ける＞"
	},
	{
		"id": 273,
		"start": 1408.1364400000007,
		"end": 1410.1364400000007,
		"text": "次回　『ワンピース』"
	},
	{
		"id": 274,
		"start": 1412.1404400000006,
		"end": 1415.1404400000006,
		"text": "海賊王に　俺は　なる！"
	},
	{
		"id": 275,
		"start": 1417.1454400000007,
		"end": 1419.1474400000006,
		"text": "＜ルフィ　エース　サボ＞"
	},
	{
		"id": 276,
		"start": 1419.1474400000006,
		"end": 1425.1474400000006,
		"text": "＜史上最強の３兄弟の<br />厚き絆を描く　感動のストーリー＞"
	},
	{
		"id": 277,
		"start": 1439.2004400000005,
		"end": 1440.7524400000007,
		"text": "（秋元・東野）おはようございます。"
	},
	{
		"id": 278,
		"start": 1440.7524400000007,
		"end": 1442.8874400000009,
		"text": "（東野）『ワイドナショー』の<br />お時間でございます。→"
	},
	{
		"id": 279,
		"start": 1442.8874400000009,
		"end": 1444.6054400000007,
		"text": "さあ　松本さん　けさはですね<br />一茂さんと　良純さんが→"
	},
	{
		"id": 280,
		"start": 1444.6054400000007,
		"end": 1447.742440000001,
		"text": "ついに　両巨頭…。"
	},
	{
		"id": 281,
		"start": 1447.742440000001,
		"end": 1449.7614400000007,
		"text": "（長嶋）巨頭？<br />（松本）すごいメンツですよね。"
	},
	{
		"id": 282,
		"start": 1449.7614400000007,
		"end": 1452.7644400000008,
		"text": "（石原）いやいや<br />別に　タッグじゃないし→"
	},
	{
		"id": 283,
		"start": 1452.7644400000008,
		"end": 1454.7494400000005,
		"text": "別に　比べられても…。<br />（松本）いや　いや　いや。"
	},
	{
		"id": 284,
		"start": 1454.7494400000005,
		"end": 1457.9854400000008,
		"text": "いつか　Ｍ－１　出てほしいな。"
	},
	{
		"id": 285,
		"start": 1457.9854400000008,
		"end": 1460.8224400000008,
		"text": "どっちが　ボケかも<br />分かんないですけどね。"
	},
	{
		"id": 286,
		"start": 1460.8224400000008,
		"end": 1462.6904400000008,
		"text": "（東野）ちょっと　笑い飯パターンでやってほしいんですけどね。"
	},
	{
		"id": 287,
		"start": 1462.6904400000008,
		"end": 1464.742440000001,
		"text": "パターンで言うと。<br />すごいわ。"
	}
]